pyrolistener/__init__.py
pyrolistener/exceptions.py
pyrolistener/listener.py
pyro_listener-2023.9.19.dist-info/LICENSE
pyro_listener-2023.9.19.dist-info/METADATA
pyro_listener-2023.9.19.dist-info/WHEEL
pyro_listener-2023.9.19.dist-info/top_level.txt
pyro_listener-2023.9.19.dist-info/RECORD
