Metadata-Version: 2.1
Name: pyro-listener
Version: 2023.9.19
Summary: Pyrogram listener
Author: ZAID
Author-email: y8838@hotmail.com
Keywords: python,pyrogram,telegram
Classifier: Development Status :: 1 - Planning
Classifier: Intended Audience :: Developers
Classifier: Programming Language :: Python :: 3
Classifier: Operating System :: Unix
Classifier: Operating System :: MacOS :: MacOS X
Classifier: Operating System :: Microsoft :: Windows
Requires-Python: ~=3.7
License-File: LICENSE
Requires-Dist: asyncio
Requires-Dist: pyrogram
